moment/__init__.py
moment/pymoment.py
pymoment-0.1.0.dist-info/LICENSE
pymoment-0.1.0.dist-info/METADATA
pymoment-0.1.0.dist-info/WHEEL
pymoment-0.1.0.dist-info/top_level.txt
pymoment-0.1.0.dist-info/RECORD
