Metadata-Version: 2.1
Name: pymoment
Version: 0.1.0
Summary: The python version of "moment" which is made with reference to "moment.js"
Home-page: https://github.com/KrixTam/pymoment
Author: Krix Tam
Author-email: krix.tam@qq.com
Project-URL: Bug Tracker, https://github.com/KrixTam/pymoment/issues
Classifier: Programming Language :: Python :: 3
Classifier: License :: OSI Approved :: MIT License
Classifier: Operating System :: OS Independent
Requires-Python: >=3.6
License-File: LICENSE
